{
  "objects": [
    {
      "type": "model",
      "file": "scene/monkey.obj",
      "material": 0
    },
    {
      "type": "plane",
      "point": [0, 3, 0],
      "normal": [0, -1, 1],
      "material": 1
    }
  ],
  "lights": [
    {
      "type": "sun",
      "direction": [0.0, 1.0, 0.0],
      "color": [0.9, 0.9, 1.0]
    },
    {
      "type": "point",
      "position": [0,0,5],
      "color": [1,1,1]
    }
  ],
  "materials": [
    {
      "color": [0.6, 0.05, 0.5],
      "specular": 0.85,
      "reflect": 0.10,
      "phong": 32
    },
    {
      "color": [0.9, 0.9, 0.9],
      "specular": 0.85,
      "reflect": 0.95,
      "phong": 32
    }
  ]
}